strictTyping/__init__.py
strictTyping/strictFunctionTyping.py
strictTyping-0.1.4.dist-info/LICENSE
strictTyping-0.1.4.dist-info/METADATA
strictTyping-0.1.4.dist-info/WHEEL
strictTyping-0.1.4.dist-info/top_level.txt
strictTyping-0.1.4.dist-info/RECORD
