Metadata-Version: 2.1
Name: strictTyping
Version: 0.1.4
License-File: LICENSE
